Workbook

Sheet 三表
A1: 项目 | B1: 2022 | C1: 2023 | D1: 2024 | E1: 2026Q1
A3: 货币资金 | B3: 1000000 | C3: 2000000 | D3: 3000000 | E3: 3500000 | H3: ='已删除的工作表'!A1
A4: 应收账款 | B4: 500000 | C4: 600000 | D4: 700000 | E4: 800000 | H4: =1/0
A5: 存货 | B5: 300000 | C5: 350000 | D5: 400000 | E5: 450000
A6: 流动资产合计 | B6: =SUM(B3:B5) | C6: =SUM(C3:C5) | D6: =SUM(D3:D5) | E6: =SUM(E3:E5)
A7: 固定资产 | B7: 2000000 | C7: 2100000 | D7: 2200000 | E7: 2300000
A8: 资产总计 | B8: =B6+B7 | C8: =C6+C7 | D8: =D6+D7 | E8: =E6+E7
A9: 短期借款 | B9: 800000 | C9: 700000 | D9: 600000 | E9: 500000
A10: 应付账款 | B10: 400000 | C10: 450000 | D10: 500000 | E10: 550000
A11: 负债合计 | B11: =B9+B10 | C11: =C9+C10 | D11: =D9+D10 | E11: =E9+E10
A12: 实收资本 | B12: 2000000 | C12: 2000000 | D12: 2000000 | E12: 2000000
A13: 未分配利润 | B13: 600000 | C13: 1900000 | D13: 3100000 | E13: 4000000
A14: 所有者权益合计 | B14: =B12+B13 | C14: =C12+C13 | D14: =D12+D13 | E14: =E12+E13
A15: 负债和所有者权益总计 | B15: =B11+B14 | C15: =C11+C14 | D15: =D11+D14+100000 | E15: =E11+E14
A17: 营业收入 | B17: 90000 | C17: 120000 | D17: 6000000 | E17: 1500000
A18: 营业成本 | B18: 60000 | C18: 80000 | D18: 4000000 | E18: 1000000
A19: 净利润 | B19: =B17-B18-20000 | C19: =C17-C18-20000 | D19: =D17-D18-20000 | E19: =E17-E18-20000
A20: 分配股利、利润或偿付利息所支付的现金 | B20: 0 | C20: 30000 | D20: 0 | E20: 0
A23: 经营活动产生的现金流量净额 | B23: 50000 | C23: 60000 | D23: 700000 | E23: 350000
A24: 投资活动产生的现金流量净额 | B24: -20000 | C24: -30000 | D24: -400000 | E24: -200000
A25: 筹资活动产生的现金流量净额 | B25: 0 | C25: 0 | D25: 0 | E25: 0
A26: 现金及现金等价物净增加额 | B26: =B23+B24+B25 | C26: =C23+C24+C25 | D26: 200000 | E26: =E23+E24+E25
A27: 期初现金及现金等价物余额 | B27: 900000 | C27: =B28 | D27: =C28 | E27: =D28
A28: 期末现金及现金等价物余额 | B28: =B27+B26 | C28: =C27+C26 | D28: =D27+D26 | E28: =E27+E26
A31: 测试公式一致性 | B31: =SUM(B3:B5) | C31: =SUM(C3:C5) | D31: =SUM(D3:D5) | E31: =SUM(E4:E5)
A32: 测试硬编码 | B32: =B8*0.5 | C32: =C8*0.5 | D32: =D8*0.5 | E32: 1234567
A34: 测试数据清洗 | B34: 1234.5 | C34: -

Sheet 比率表
A1: 指标 | B1: 2022 | C1: 2023 | D1: 2024 | E1: 2026Q1
A2: 应收账款周转天数 | B2: =365*'三表'!B4/'三表'!B17 | C2: =365*'三表'!C4/'三表'!C17 | D2: =365*'三表'!D4/'三表'!D17 | E2: =365*'三表'!E4/'三表'!E17
A3: 应付账款周转天数 | B3: =365*'三表'!B10/'三表'!B18 | C3: =365*'三表'!C10/'三表'!C18 | D3: =365*'三表'!D10/'三表'!D18 | E3: =365*'三表'!E10/'三表'!E18
A4: 净利率 | B4: ='三表'!B19/'三表'!B17 | C4: ='三表'!C19/'三表'!C17 | D4: ='三表'!D19/'三表'!D17 | E4: ='三表'!E19/'三表'!E17
A5: 有息负债合计 | B5: ='三表'!B9 | C5: ='三表'!C9 | D5: ='三表'!D9 | E5: ='三表'!E9
A6: 现金转换周期 | B6: =B2+30-B3 | C6: =C2+30-C3 | D6: =D2+30-D3 | E6: =E2+30-E3
A7: 流动比率 | B7: ='三表'!B6/0 | C7: ='三表'!C6/'三表'!C9 | D7: ='三表'!D6/'三表'!D9 | E7: ='三表'!E6/'三表'!E9

Sheet 数据
A1: 科目 | B1: 金额
A2: 营业收入 | B2: 1234.5
A3: 营业成本 | B3: -
A4: 销售费用
A5: 管理费用 | B5: 100
A6: 管理费用 | B6: 100
A7: 财务费用 | B7: 50
